bunya_jobs/__init__.py
bunya_jobs/monitor.py
bunya_jobs/hooks/__init__.py
bunya_jobs/hooks/slack.py
bunya_jobs/utils/__init__.py
bunya_jobs/utils/data_processing.py
bunya_jobs-0.1.7.dist-info/LICENSE
bunya_jobs-0.1.7.dist-info/METADATA
bunya_jobs-0.1.7.dist-info/WHEEL
bunya_jobs-0.1.7.dist-info/top_level.txt
bunya_jobs-0.1.7.dist-info/RECORD
