Metadata-Version: 2.1
Name: bunya_jobs
Version: 0.1.7
Summary: useful utilities for monitoring jobs at bunya
Author-email: Kerry Chu <kerry.x.chu@gmail.com>
Classifier: Programming Language :: Python :: 3
Classifier: License :: OSI Approved :: MIT License
Classifier: Operating System :: OS Independent
Requires-Python: >=3.9
License-File: LICENSE
